gseagui/__init__.py
gseagui/enrichment_tools.py
gseagui/gmt_generator.py
gseagui/gsea_res_ploter.py
gseagui/gsea_runner.py
gseagui/main.py
gseagui/qt_utils.py
gseagui/translations.py
gseagui-0.1.9.dist-info/licenses/LICENSE
gseagui-0.1.9.dist-info/METADATA
gseagui-0.1.9.dist-info/WHEEL
gseagui-0.1.9.dist-info/entry_points.txt
gseagui-0.1.9.dist-info/top_level.txt
gseagui-0.1.9.dist-info/RECORD
