Metadata-Version: 2.4
Name: gseagui
Version: 0.1.9
Summary: GUI tools for gene set enrichment analysis
Author-email: Qing <byeomax@outlook.com>
License: BSD-3-Clause
Project-URL: Homepage, https://github.com/byemaxx/gseaGUI
Project-URL: Bug Tracker, https://github.com/byemaxx/gseaGUI/issues
Keywords: bioinformatics,GSEA,GUI
Classifier: Development Status :: 3 - Alpha
Classifier: Intended Audience :: Science/Research
Classifier: Programming Language :: Python :: 3
Classifier: Topic :: Scientific/Engineering :: Bio-Informatics
Classifier: License :: OSI Approved :: BSD License
Requires-Python: >=3.10
License-File: LICENSE
Requires-Dist: pandas
Requires-Dist: numpy
Requires-Dist: matplotlib
Requires-Dist: gseapy
Requires-Dist: PyQt5
Dynamic: license-file
